{"version": "1", "message": "ERROR: Hidden Testcases server unreachable.", "problem_id": "ads1_m14_a2", "user_id": "GundetiGnanika-20186026", "score": {"sample": {"0": {"execution_time": 0.3289480209350586, "passed": true}, "1": {"execution_time": 0.3407313823699951, "passed": true}, "2": {"execution_time": 0.45902442932128906, "passed": true}, "3": {"execution_time": 0.35526418685913086, "passed": false}, "4": {"execution_time": 0.3494727611541748, "passed": false}, "5": {"execution_time": 0.4206547737121582, "passed": true}}}, "check_style_score": "0/1"}